mbedext/__init__.py
mbedext/example.py
mbedext/utils.py
mbedext/clusterer/__init__.py
mbedext/clusterer/clusterer.py
mbedext/clusterer/sklearn_clusterer.py
mbedext/embedder/__init__.py
mbedext/embedder/embedder.py
mbedext/embedder/hf_embedder.py
mbedext/embedder/st_embedder.py
mbedext/mbedder/__init__.py
mbedext/mbedder/mbedder.py
mbedext/visualizer/__init__.py
mbedext/visualizer/visualizer.py
mbedext/visualizer/reducer/__init__.py
mbedext/visualizer/reducer/reducer.py
mbedext/visualizer/reducer/sklearn_reducer.py
mbedext-0.0.11.dist-info/LICENSE
mbedext-0.0.11.dist-info/METADATA
mbedext-0.0.11.dist-info/WHEEL
mbedext-0.0.11.dist-info/top_level.txt
mbedext-0.0.11.dist-info/RECORD
